kvcdl/__init__.py
kvcdl/args.py
kvcdl/certificate.py
kvcdl/config.py
kvcdl/hook.py
kvcdl/keyvault.py
kvcdl/main.py
kvcdl/models.py
kvcdl/output.py
kvcdl-0.2.9.dist-info/LICENSE
kvcdl-0.2.9.dist-info/METADATA
kvcdl-0.2.9.dist-info/WHEEL
kvcdl-0.2.9.dist-info/entry_points.txt
kvcdl-0.2.9.dist-info/top_level.txt
kvcdl-0.2.9.dist-info/RECORD
