Metadata-Version: 2.1
Name: kvcdl
Version: 0.2.9
Summary: Download certificate secrets from Azure Key Vault
Home-page: https://git.faithlife.dev/Logos/keyvault-cert-downloader
Author: Travis Brackett
Author-email: travmeister@gmail.com
Classifier: Programming Language :: Python :: 3
Classifier: License :: OSI Approved :: MIT License
Classifier: Operating System :: POSIX :: Linux
Requires-Python: >=3.6
License-File: LICENSE
Requires-Dist: pyyaml >=5.4.1
Requires-Dist: azure-identity >=1.6.0
Requires-Dist: azure-keyvault-secrets >=4.3.0
Requires-Dist: cryptography >=3.4.7
Requires-Dist: dbus-python >=1.2.16
Requires-Dist: xattr >=0.9.7
